{
    "AutoStart": {
        "client": "localhost:6742",
        "custom": "",
        "enabled": true,
        "host": "0.0.0.0",
        "port": "",
        "profile": "Light green",
        "setclient": false,
        "setcustom": false,
        "setminimized": true,
        "setprofile": true,
        "setserver": false,
        "setserverhost": false,
        "setserverport": false
    },
    "CorsairDominatorSettings": {
        "model": "CMT"
    },
    "Detectors": {
        "detectors": {
            "AMD Wraith Prism": false,
            "AOC AGON AMM700": false,
            "AOC GK500": false,
            "AOC GM500": false,
            "ASRock Deskmini Addressable LED Strip": false,
            "ASRock Motherboard SMBus Controllers": false,
            "ASRock Polychrome USB": false,
            "ASUS AREZ Strix RX Vega 56 O8G": false,
            "ASUS Aura Addressable": true,
            "ASUS Aura Core": true,
            "ASUS Aura Motherboard": true,
            "ASUS Aura SMBus Motherboard": true,
            "ASUS Cerberus Mech": false,
            "ASUS GTX 1060 Strix": false,
            "ASUS GTX 1060 Strix 6G Gaming": false,
            "ASUS GTX 1070 Strix Gaming": false,
            "ASUS GTX 1070 Strix OC": false,
            "ASUS GTX 1080 Strix OC": false,
            "ASUS KO RTX 3060 O12G V2 GAMING": false,
            "ASUS KO RTX 3060 OC O12G GAMING": false,
            "ASUS KO RTX 3060Ti O8G GAMING": false,
            "ASUS KO RTX 3060Ti O8G V2 GAMING": false,
            "ASUS KO RTX 3070 O8G V2 GAMING": false,
            "ASUS ROG AURA Terminal": true,
            "ASUS ROG Ally": false,
            "ASUS ROG Balteus": false,
            "ASUS ROG Balteus Qi": false,
            "ASUS ROG Chakram (Wireless)": false,
            "ASUS ROG Claymore": false,
            "ASUS ROG Falchion (Wired)": false,
            "ASUS ROG Falchion (Wireless)": false,
            "ASUS ROG GTX 1660 Ti OC 6G": false,
            "ASUS ROG Gladius II": false,
            "ASUS ROG Gladius II Core": false,
            "ASUS ROG Gladius II Origin": false,
            "ASUS ROG Gladius II Origin COD": false,
            "ASUS ROG Gladius II Origin PNK LTD": false,
            "ASUS ROG Gladius II Wireless": false,
            "ASUS ROG Gladius III": false,
            "ASUS ROG Gladius III Wireless 2.4Ghz": false,
            "ASUS ROG Gladius III Wireless Bluetooth": false,
            "ASUS ROG Gladius III Wireless USB": false,
            "ASUS ROG Keris": false,
            "ASUS ROG Keris Wireless 2.4Ghz": false,
            "ASUS ROG Keris Wireless Bluetooth": false,
            "ASUS ROG Keris Wireless USB": false,
            "ASUS ROG PG32UQ": false,
            "ASUS ROG Pugio": false,
            "ASUS ROG Pugio II (Wired)": false,
            "ASUS ROG Pugio II (Wireless)": false,
            "ASUS ROG RTX 3080 10G GUNDAM EDITION": false,
            "ASUS ROG Ryuo AIO": false,
            "ASUS ROG STRIX 3060 12G GAMING": false,
            "ASUS ROG STRIX 3060 O12G GAMING": false,
            "ASUS ROG STRIX 3060 O12G V2 GAMING": false,
            "ASUS ROG STRIX 3060Ti O8G OC": false,
            "ASUS ROG STRIX 3060Ti O8G V2": false,
            "ASUS ROG STRIX 3070 O8G GAMING": false,
            "ASUS ROG STRIX 3070 O8G V2 GAMING": false,
            "ASUS ROG STRIX 3070 O8G V2 White": false,
            "ASUS ROG STRIX 3070 O8G White": false,
            "ASUS ROG STRIX 3070 OC": false,
            "ASUS ROG STRIX 3070Ti O8G GAMING": false,
            "ASUS ROG STRIX 3080 10G GAMING": false,
            "ASUS ROG STRIX 3080 10G V2 GAMING": false,
            "ASUS ROG STRIX 3080 O10G GAMING": false,
            "ASUS ROG STRIX 3080 O10G V2 GAMING": false,
            "ASUS ROG STRIX 3080 O10G V2 WHITE": false,
            "ASUS ROG STRIX 3080 O10G WHITE": false,
            "ASUS ROG STRIX 3080Ti O12G GAMING": false,
            "ASUS ROG STRIX 3090 24G GAMING": false,
            "ASUS ROG STRIX 3090 O24G GAMING": false,
            "ASUS ROG STRIX 3090 O24G GAMING White OC": false,
            "ASUS ROG STRIX LC 3080Ti O12G GAMING": false,
            "ASUS ROG STRIX LC RX 6800XT O16G GAMING": false,
            "ASUS ROG STRIX LC RX 6900XT O16G GAMING": false,
            "ASUS ROG STRIX LC RX 6900XT O16G GAMING TOP": false,
            "ASUS ROG STRIX LC RX 6950XT O16G GAMING": false,
            "ASUS ROG STRIX RTX 2060 EVO Gaming 6G": false,
            "ASUS ROG STRIX RTX 2060 O6G EVO Gaming": false,
            "ASUS ROG STRIX RTX 2060 O6G Gaming": false,
            "ASUS ROG STRIX RTX 2060S 8G Gaming": false,
            "ASUS ROG STRIX RTX 2060S A8G EVO Gaming": false,
            "ASUS ROG STRIX RTX 2060S A8G Gaming": false,
            "ASUS ROG STRIX RTX 2060S O8G Gaming": false,
            "ASUS ROG STRIX RTX 2070 A8G Gaming": false,
            "ASUS ROG STRIX RTX 2070 O8G Gaming": false,
            "ASUS ROG STRIX RTX 2070S 8G Gaming": false,
            "ASUS ROG STRIX RTX 2070S A8G Gaming": false,
            "ASUS ROG STRIX RTX 2070S O8G Gaming": false,
            "ASUS ROG STRIX RTX 2080 8G Gaming": false,
            "ASUS ROG STRIX RTX 2080 O8G Gaming": false,
            "ASUS ROG STRIX RTX 2080 O8G V2 Gaming": false,
            "ASUS ROG STRIX RTX 2080 Ti 11G Gaming": false,
            "ASUS ROG STRIX RTX 2080 Ti A11G Gaming": false,
            "ASUS ROG STRIX RTX 2080 Ti O11G Gaming": false,
            "ASUS ROG STRIX RTX 2080S A8G Gaming": false,
            "ASUS ROG STRIX RTX 2080S O8G Gaming": false,
            "ASUS ROG STRIX RTX 2080S O8G White": false,
            "ASUS ROG STRIX RTX 3080 12G": false,
            "ASUS ROG STRIX RTX 3080 O12G": false,
            "ASUS ROG STRIX RTX 3080 O12G EVA EDITION": false,
            "ASUS ROG STRIX RTX 4080 16G GAMING": false,
            "ASUS ROG STRIX RTX 4080 O16G GAMING": false,
            "ASUS ROG STRIX RTX 4090 24G GAMING": false,
            "ASUS ROG STRIX RTX 4090 O24G GAMING": false,
            "ASUS ROG STRIX RX 6700XT O12G GAMING": false,
            "ASUS ROG STRIX RX 6750XT O12G GAMING": false,
            "ASUS ROG STRIX RX 6800 O16G Gaming": false,
            "ASUS ROG STRIX RX470 O4G Gaming": false,
            "ASUS ROG STRIX RX480 Gaming OC": false,
            "ASUS ROG STRIX RX560 Gaming": false,
            "ASUS ROG Strix Claw": false,
            "ASUS ROG Strix Evolve": false,
            "ASUS ROG Strix Flare": false,
            "ASUS ROG Strix Flare CoD Black Ops 4 Edition": false,
            "ASUS ROG Strix Flare PNK LTD": false,
            "ASUS ROG Strix GTX 1050 O2G Gaming": false,
            "ASUS ROG Strix GTX 1050 TI 4G Gaming": false,
            "ASUS ROG Strix GTX 1050 TI O4G Gaming": false,
            "ASUS ROG Strix GTX 1650S OC 4G": false,
            "ASUS ROG Strix GTX 1660S O6G Gaming": false,
            "ASUS ROG Strix GTX1070 Ti 8G Gaming": false,
            "ASUS ROG Strix GTX1070 Ti A8G Gaming": false,
            "ASUS ROG Strix GTX1080 A8G Gaming": false,
            "ASUS ROG Strix GTX1080 O8G 11Gbps": false,
            "ASUS ROG Strix GTX1080 O8G Gaming": false,
            "ASUS ROG Strix GTX1080 Ti 11G Gaming": false,
            "ASUS ROG Strix GTX1080 Ti Gaming": false,
            "ASUS ROG Strix GTX1080 Ti O11G Gaming": false,
            "ASUS ROG Strix Impact": false,
            "ASUS ROG Strix Impact II": false,
            "ASUS ROG Strix Impact II Electro Punk": false,
            "ASUS ROG Strix Impact II Gundam": false,
            "ASUS ROG Strix Impact II Moonlight White": false,
            "ASUS ROG Strix Impact II Wireless 2.4 Ghz": false,
            "ASUS ROG Strix Impact II Wireless USB": false,
            "ASUS ROG Strix LC": false,
            "ASUS ROG Strix SCAR 15": false,
            "ASUS ROG Strix Scope": false,
            "ASUS ROG Strix Scope RX": false,
            "ASUS ROG Strix Scope RX TKL Wireless Deluxe": false,
            "ASUS ROG Strix Scope TKL": false,
            "ASUS ROG Strix Scope TKL PNK LTD": false,
            "ASUS ROG Strix XG279Q": false,
            "ASUS ROG Strix XG27AQ": false,
            "ASUS ROG Strix XG27AQM": false,
            "ASUS ROG Strix XG27W": false,
            "ASUS ROG Throne": false,
            "ASUS ROG Throne QI": false,
            "ASUS ROG Throne QI GUNDAM": false,
            "ASUS RX 5600XT Strix O6G Gaming": false,
            "ASUS RX 570 Strix O4G Gaming OC": false,
            "ASUS RX 570 Strix O8G Gaming OC": false,
            "ASUS RX 5700XT Strix 08G Gaming": false,
            "ASUS RX 5700XT Strix Gaming OC": false,
            "ASUS RX 580 Strix Gaming OC": false,
            "ASUS RX 580 Strix Gaming TOP": false,
            "ASUS RX 6800 TUF Gaming OC": false,
            "ASUS TUF 3060 O12G GAMING": false,
            "ASUS TUF 3060 O12G V2 GAMING": false,
            "ASUS TUF Gaming K1": false,
            "ASUS TUF Gaming K3": false,
            "ASUS TUF Gaming K5": false,
            "ASUS TUF Gaming K7": false,
            "ASUS TUF Gaming M3": false,
            "ASUS TUF Gaming M5": false,
            "ASUS TUF Laptop": true,
            "ASUS TUF RTX 3060 Ti 8G Gaming OC": false,
            "ASUS TUF RTX 3060Ti O8G": false,
            "ASUS TUF RTX 3060Ti O8G OC": false,
            "ASUS TUF RTX 3070 8G GAMING": false,
            "ASUS TUF RTX 3070 O8G GAMING": false,
            "ASUS TUF RTX 3070 O8G V2 GAMING": false,
            "ASUS TUF RTX 3070Ti O8G GAMING": false,
            "ASUS TUF RTX 3070Ti O8G V2 GAMING": false,
            "ASUS TUF RTX 3080 10G GAMING": false,
            "ASUS TUF RTX 3080 O10G OC": false,
            "ASUS TUF RTX 3080 O10G V2 GAMING": false,
            "ASUS TUF RTX 3080 O12G GAMING": false,
            "ASUS TUF RTX 3080Ti 12G GAMING": false,
            "ASUS TUF RTX 3080Ti O12G GAMING": false,
            "ASUS TUF RTX 3090 O24G": false,
            "ASUS TUF RTX 3090 O24G OC": false,
            "ASUS TUF RTX 3090Ti O24G OC GAMING": false,
            "ASUS TUF RTX 4070 Ti 12G Gaming": false,
            "ASUS TUF RTX 4070 Ti O12G Gaming": false,
            "ASUS TUF RTX 4080 O16G GAMING": false,
            "ASUS TUF RTX 4080 O16G OC": false,
            "ASUS TUF RTX 4090 O24G": false,
            "ASUS TUF RTX 4090 O24G OC": false,
            "ASUS TUF RX 6700XT O12G GAMING": false,
            "ASUS TUF RX 6800XT O16G GAMING": false,
            "ASUS TUF RX 6900XT O16G GAMING": false,
            "ASUS TUF RX 6900XT T16G GAMING": false,
            "ASUS TUF RX 6950XT O16G GAMING": false,
            "ASUS Vega 64 Strix": false,
            "Acer Predator Gaming Mouse (Rival 300)": false,
            "Alienware AW510K": false,
            "Anne Pro 2": false,
            "Aorus CPU Coolers": false,
            "Asus ROG Chakram (Wired)": false,
            "Asus ROG Chakram Core": false,
            "Asus ROG Chakram X 2.4GHz": false,
            "Asus ROG Chakram X USB": false,
            "Asus ROG Spatha X 2.4GHz": false,
            "Asus ROG Spatha X USB": false,
            "BlinkyTape": false,
            "Bloody MP 50RS": false,
            "Bloody W60 Pro": false,
            "CRYORIG H7 Quad Lumi": false,
            "Cherry Keyboard CCF MX 1.0 TKL BL": false,
            "Cherry Keyboard CCF MX 1.0 TKL NBL": false,
            "Cherry Keyboard CCF MX 8.0 TKL BL": false,
            "Cherry Keyboard G80-3000 TKL NBL": false,
            "Cherry Keyboard G80-3000 TKL NBL KOREAN": false,
            "Cherry Keyboard G80-3000 TKL RGB": false,
            "Cherry Keyboard G80-3000N FL RGB": false,
            "Cherry Keyboard G80-3000N TKL RGB": false,
            "Cherry Keyboard MV BOARD 3.0 FL RGB": false,
            "Cherry Keyboard MX 1.0 FL BL": false,
            "Cherry Keyboard MX 1.0 FL NBL": false,
            "Cherry Keyboard MX 1.0 FL RGB": false,
            "Cherry Keyboard MX BOARD 1.0 TKL RGB": false,
            "Cherry Keyboard MX BOARD 10.0 FL RGB": false,
            "Cherry Keyboard MX BOARD 10.0N FL RGB": false,
            "Cherry Keyboard MX BOARD 2.0S FL NBL": false,
            "Cherry Keyboard MX BOARD 2.0S FL RGB": false,
            "Cherry Keyboard MX BOARD 2.0S FL RGB DE": false,
            "Cherry Keyboard MX BOARD 3.0S FL NBL": false,
            "Cherry Keyboard MX BOARD 3.0S FL RGB": false,
            "Cherry Keyboard MX BOARD 3.0S FL RGB KOREAN": false,
            "Cherry Keyboard MX BOARD 8.0 TKL RGB": false,
            "Cooler Master ARGB": false,
            "Cooler Master ARGB Gen 2 A1": false,
            "Cooler Master ARGB Gen 2 A1 V2": false,
            "Cooler Master MK750": false,
            "Cooler Master MM530": false,
            "Cooler Master MM711": false,
            "Cooler Master MM720": false,
            "Cooler Master MM730": false,
            "Cooler Master MP750 Large": false,
            "Cooler Master MP750 Medium": false,
            "Cooler Master MP750 XL": false,
            "Cooler Master MasterKeys Pro L": false,
            "Cooler Master MasterKeys Pro L White": false,
            "Cooler Master MasterKeys Pro S": false,
            "Cooler Master RGB": false,
            "Cooler Master Radeon 6000 GPU": false,
            "Cooler Master Radeon 6900 GPU": false,
            "Cooler Master SK630": false,
            "Cooler Master SK650": false,
            "Cooler Master Small ARGB": false,
            "Corsair 1000D Obsidian": false,
            "Corsair Commander Core": false,
            "Corsair Commander Pro": false,
            "Corsair Dominator Platinum": false,
            "Corsair Glaive RGB": false,
            "Corsair Glaive RGB PRO": false,
            "Corsair H100i v2": false,
            "Corsair Harpoon RGB": false,
            "Corsair Harpoon RGB PRO": false,
            "Corsair Hydro H100i Platinum": false,
            "Corsair Hydro H100i Platinum SE": false,
            "Corsair Hydro H100i Pro XT": false,
            "Corsair Hydro H100i Pro XT v2": false,
            "Corsair Hydro H115i Platinum": false,
            "Corsair Hydro H115i Pro XT": false,
            "Corsair Hydro H150i Pro XT": false,
            "Corsair Hydro H60i Pro XT": false,
            "Corsair Hydro Series": false,
            "Corsair Ironclaw RGB": false,
            "Corsair Ironclaw Wireless": false,
            "Corsair Ironclaw Wireless (Wired)": false,
            "Corsair K100": false,
            "Corsair K55 RGB": false,
            "Corsair K55 RGB PRO": false,
            "Corsair K55 RGB PRO XT": false,
            "Corsair K57 RGB (Wired)": false,
            "Corsair K60 RGB PRO": false,
            "Corsair K60 RGB PRO Low Profile": false,
            "Corsair K65 LUX RGB": false,
            "Corsair K65 Mini": false,
            "Corsair K65 RGB": false,
            "Corsair K65 RGB RAPIDFIRE": false,
            "Corsair K68 RGB": false,
            "Corsair K70 LUX": false,
            "Corsair K70 LUX RGB": false,
            "Corsair K70 RGB": false,
            "Corsair K70 RGB MK.2": false,
            "Corsair K70 RGB MK.2 Low Profile": false,
            "Corsair K70 RGB MK.2 SE": false,
            "Corsair K70 RGB RAPIDFIRE": false,
            "Corsair K95 RGB": false,
            "Corsair K95 RGB PLATINUM": false,
            "Corsair K95 RGB PLATINUM XT": false,
            "Corsair LS100 Lighting Kit": false,
            "Corsair LT100": false,
            "Corsair Lighting Node Core": false,
            "Corsair Lighting Node Pro": false,
            "Corsair M55 RGB PRO": false,
            "Corsair M65": false,
            "Corsair M65 PRO": false,
            "Corsair M65 RGB Elite": false,
            "Corsair MM700": false,
            "Corsair MM800 RGB Polaris": false,
            "Corsair Nightsword": false,
            "Corsair SPEC OMEGA RGB": false,
            "Corsair ST100 RGB": false,
            "Corsair Sabre RGB": false,
            "Corsair Scimitar Elite RGB": false,
            "Corsair Scimitar PRO RGB": false,
            "Corsair Scimitar RGB": false,
            "Corsair Strafe": false,
            "Corsair Strafe MK.2": false,
            "Corsair Strafe Red": false,
            "Corsair Vengeance": false,
            "Corsair Vengeance Pro": false,
            "Cougar 700K EVO Gaming Keyboard": false,
            "Cougar Revenger ST": false,
            "Creative SoundBlasterX G6": false,
            "Crucial": false,
            "DMX": false,
            "Dark Project KD3B V2": false,
            "Das Keyboard Q4 RGB": false,
            "Das Keyboard Q5 RGB": false,
            "Das Keyboard Q5S RGB": false,
            "Debug Controllers": false,
            "Dell G Series LED Controller": false,
            "Ducky One 2 RGB TKL": false,
            "Ducky Shine 7/Ducky One 2 RGB": false,
            "Dygma Raise": false,
            "E1.31": false,
            "EK Loop Connect": false,
            "ENE SMBus DRAM": false,
            "EVGA GP102 GPU": false,
            "EVGA GeForce RTX 2070 SUPER FTW3 Ultra": false,
            "EVGA GeForce RTX 2070 SUPER FTW3 Ultra+": false,
            "EVGA GeForce RTX 2070 SUPER XC Gaming": false,
            "EVGA GeForce RTX 2070 SUPER XC Ultra": false,
            "EVGA GeForce RTX 2070 SUPER XC Ultra+": false,
            "EVGA GeForce RTX 2070 XC Black": false,
            "EVGA GeForce RTX 2070 XC Gaming": false,
            "EVGA GeForce RTX 2070 XC OC": false,
            "EVGA GeForce RTX 2080 Black": false,
            "EVGA GeForce RTX 2080 SUPER FTW3 Hybrid OC": false,
            "EVGA GeForce RTX 2080 SUPER FTW3 Ultra": false,
            "EVGA GeForce RTX 2080 SUPER FTW3 Ultra Hydro Copper": false,
            "EVGA GeForce RTX 2080 SUPER XC Gaming": false,
            "EVGA GeForce RTX 2080 SUPER XC Ultra": false,
            "EVGA GeForce RTX 2080 XC Black": false,
            "EVGA GeForce RTX 2080 XC Gaming": false,
            "EVGA GeForce RTX 2080 XC Ultra Gaming": false,
            "EVGA GeForce RTX 2080Ti Black": false,
            "EVGA GeForce RTX 2080Ti FTW3 Ultra": false,
            "EVGA GeForce RTX 2080Ti XC HYBRID GAMING": false,
            "EVGA GeForce RTX 2080Ti XC HYDRO COPPER": false,
            "EVGA GeForce RTX 2080Ti XC Ultra": false,
            "EVGA GeForce RTX 3060TI FTW3 Gaming": false,
            "EVGA GeForce RTX 3060TI FTW3 Ultra": false,
            "EVGA GeForce RTX 3060TI FTW3 Ultra LHR": false,
            "EVGA GeForce RTX 3070 Black Gaming": false,
            "EVGA GeForce RTX 3070 FTW3 Ultra": false,
            "EVGA GeForce RTX 3070 FTW3 Ultra LHR": false,
            "EVGA GeForce RTX 3070 XC3 Gaming": false,
            "EVGA GeForce RTX 3070 XC3 Ultra": false,
            "EVGA GeForce RTX 3070 XC3 Ultra LHR": false,
            "EVGA GeForce RTX 3070Ti FTW3 Ultra": false,
            "EVGA GeForce RTX 3070Ti FTW3 Ultra v2": false,
            "EVGA GeForce RTX 3070Ti XC3 Gaming": false,
            "EVGA GeForce RTX 3070Ti XC3 Ultra": false,
            "EVGA GeForce RTX 3070Ti XC3 Ultra v2": false,
            "EVGA GeForce RTX 3080 FTW3 Gaming": false,
            "EVGA GeForce RTX 3080 FTW3 Ultra": false,
            "EVGA GeForce RTX 3080 FTW3 Ultra 12GB": false,
            "EVGA GeForce RTX 3080 FTW3 Ultra Hybrid": false,
            "EVGA GeForce RTX 3080 FTW3 Ultra Hybrid Gaming LHR": false,
            "EVGA GeForce RTX 3080 FTW3 Ultra Hybrid LHR": false,
            "EVGA GeForce RTX 3080 FTW3 Ultra Hydro Copper": false,
            "EVGA GeForce RTX 3080 FTW3 Ultra Hydro Copper 12G": false,
            "EVGA GeForce RTX 3080 FTW3 Ultra LHR": false,
            "EVGA GeForce RTX 3080 FTW3 Ultra v2 LHR": false,
            "EVGA GeForce RTX 3080 XC3 Black": false,
            "EVGA GeForce RTX 3080 XC3 Black LHR": false,
            "EVGA GeForce RTX 3080 XC3 Gaming": false,
            "EVGA GeForce RTX 3080 XC3 Gaming LHR": false,
            "EVGA GeForce RTX 3080 XC3 Ultra": false,
            "EVGA GeForce RTX 3080 XC3 Ultra 12G": false,
            "EVGA GeForce RTX 3080 XC3 Ultra Hybrid": false,
            "EVGA GeForce RTX 3080 XC3 Ultra Hybrid LHR": false,
            "EVGA GeForce RTX 3080 XC3 Ultra Hydro Copper": false,
            "EVGA GeForce RTX 3080 XC3 Ultra LHR": false,
            "EVGA GeForce RTX 3080Ti FTW3 Ultra": false,
            "EVGA GeForce RTX 3080Ti FTW3 Ultra Hybrid": false,
            "EVGA GeForce RTX 3080Ti FTW3 Ultra Hydro Copper": false,
            "EVGA GeForce RTX 3080Ti XC3 Gaming": false,
            "EVGA GeForce RTX 3080Ti XC3 Gaming Hybrid": false,
            "EVGA GeForce RTX 3080Ti XC3 Gaming Hydro Copper": false,
            "EVGA GeForce RTX 3080Ti XC3 Ultra Gaming": false,
            "EVGA GeForce RTX 3090 FTW3 Ultra": false,
            "EVGA GeForce RTX 3090 FTW3 Ultra Hybrid": false,
            "EVGA GeForce RTX 3090 FTW3 Ultra Hydro Copper": false,
            "EVGA GeForce RTX 3090 FTW3 Ultra v2": false,
            "EVGA GeForce RTX 3090 FTW3 Ultra v3": false,
            "EVGA GeForce RTX 3090 K|NGP|N Hybrid": false,
            "EVGA GeForce RTX 3090 K|NGP|N Hydro Copper": false,
            "EVGA GeForce RTX 3090 XC3 Black": false,
            "EVGA GeForce RTX 3090 XC3 Gaming": false,
            "EVGA GeForce RTX 3090 XC3 Ultra": false,
            "EVGA GeForce RTX 3090 XC3 Ultra Hybrid": false,
            "EVGA GeForce RTX 3090 XC3 Ultra Hydro Copper": false,
            "EVGA GeForce RTX 3090Ti FTW3 Black Gaming": false,
            "EVGA GeForce RTX 3090Ti FTW3 Gaming": false,
            "EVGA GeForce RTX 3090Ti FTW3 Ultra Gaming": false,
            "EVGA Pascal GPU": false,
            "EVGA X20 Gaming Mouse": false,
            "EVGA X20 USB Receiver": false,
            "EVGA Z15 Keyboard": false,
            "EVGA Z20 Keyboard": false,
            "EVision Keyboard 0C45:5004": false,
            "EVision Keyboard 0C45:5104": false,
            "EVision Keyboard 0C45:5204": false,
            "EVision Keyboard 0C45:652F": false,
            "EVision Keyboard 0C45:7698": false,
            "EVision Keyboard 0C45:8520": false,
            "EVision Keyboard 320F:5000": false,
            "EVision Keyboard 320F:502A": false,
            "EVision Keyboard 320F:5064": false,
            "ElgatoKeyLight": false,
            "Epomaker TH80 Pro (USB Cable)": false,
            "Epomaker TH80 Pro (USB Dongle)": false,
            "Espurna": false,
            "Everest GT-100 RGB": false,
            "FanBus": false,
            "Faustus": true,
            "GALAX RTX 2070 Super EX Gamer Black": false,
            "GaiZhongGai 17 PRO": false,
            "GaiZhongGai 17+4+Touch PRO": false,
            "GaiZhongGai 20 PRO": false,
            "GaiZhongGai 42 PRO": false,
            "GaiZhongGai 68+4 PRO": false,
            "GaiZhongGai Dial": false,
            "GaiZhongGai LightBoard": false,
            "GaiZhongGai RGB HUB Blue": false,
            "GaiZhongGai RGB HUB Green": false,
            "Gainward GTX 1080 Phoenix": false,
            "Gainward GTX 1080 Ti Phoenix": false,
            "Gainward RTX 2070 Super Phantom": false,
            "Gainward RTX 2080 Phoenix GS": false,
            "Gainward RTX 3070 Phoenix": false,
            "Gainward RTX 3070 Ti Phoenix": false,
            "Gainward RTX 3080 Phoenix": false,
            "Gainward RTX 3080 Ti Phoenix": false,
            "Gainward RTX 3090 Phoenix": false,
            "Genesis Thor 300": false,
            "Gigabyte AORUS RTX2060 SUPER 8G V1": false,
            "Gigabyte AORUS RTX2070 SUPER 8G": false,
            "Gigabyte AORUS RTX2070 XTREME 8G": false,
            "Gigabyte AORUS RTX2080 8G": false,
            "Gigabyte AORUS RTX2080 SUPER 8G": false,
            "Gigabyte AORUS RTX2080 SUPER 8G Rev 1.0": false,
            "Gigabyte AORUS RTX2080 SUPER Waterforce WB 8G": false,
            "Gigabyte AORUS RTX2080 Ti XTREME 11G": false,
            "Gigabyte AORUS RTX2080 XTREME 8G": false,
            "Gigabyte AORUS RTX3060 ELITE 12G": false,
            "Gigabyte AORUS RTX3060 ELITE 12G LHR": false,
            "Gigabyte AORUS RTX3060 ELITE 12G Rev a1": false,
            "Gigabyte AORUS RTX3060 Ti ELITE 8G LHR": false,
            "Gigabyte AORUS RTX3070 Ti MASTER 8G": false,
            "Gigabyte AORUS RTX3080 Ti XTREME WATERFORCE 12G": false,
            "Gigabyte AORUS RTX3080 XTREME WATERFORCE 10G Rev 2.0": false,
            "Gigabyte AORUS RTX3080 XTREME WATERFORCE WB 10G": false,
            "Gigabyte AORUS RTX3080 XTREME WATERFORCE WB 12G LHR": false,
            "Gigabyte AORUS RTX3090 XTREME WATERFORCE 24G": false,
            "Gigabyte AORUS RTX3090 XTREME WATERFORCE WB 24G": false,
            "Gigabyte AORUS RTX4080 MASTER 16G": false,
            "Gigabyte AORUS RTX4090 MASTER 24G": false,
            "Gigabyte Aorus M2": false,
            "Gigabyte GTX1050 Ti G1 Gaming": false,
            "Gigabyte GTX1050 Ti G1 Gaming (rev A1)": false,
            "Gigabyte GTX1060 G1 Gaming 6G": false,
            "Gigabyte GTX1060 G1 Gaming 6G OC": false,
            "Gigabyte GTX1060 Xtreme Gaming V1": false,
            "Gigabyte GTX1060 Xtreme Gaming v2": false,
            "Gigabyte GTX1070 G1 Gaming 8G V1": false,
            "Gigabyte GTX1070 Ti 8G Gaming": false,
            "Gigabyte GTX1070 Xtreme Gaming": false,
            "Gigabyte GTX1080 G1 Gaming": false,
            "Gigabyte GTX1080 Ti 11G": false,
            "Gigabyte GTX1080 Ti Gaming OC 11G": false,
            "Gigabyte GTX1080 Ti Gaming OC BLACK 11G": false,
            "Gigabyte GTX1080 Ti Xtreme Edition": false,
            "Gigabyte GTX1080 Ti Xtreme Waterforce Edition": false,
            "Gigabyte GTX1650 Gaming OC": false,
            "Gigabyte GTX1660 Gaming OC 6G": false,
            "Gigabyte GTX1660 SUPER Gaming OC": false,
            "Gigabyte RGB": false,
            "Gigabyte RGB Fusion": false,
            "Gigabyte RGB Fusion 2 DRAM": false,
            "Gigabyte RGB Fusion 2 SMBus": false,
            "Gigabyte RGB Fusion 2 USB": false,
            "Gigabyte RTX2060 Gaming OC": false,
            "Gigabyte RTX2060 Gaming OC PRO": false,
            "Gigabyte RTX2060 Gaming OC PRO V2": false,
            "Gigabyte RTX2060 Gaming OC PRO White": false,
            "Gigabyte RTX2060 SUPER Gaming": false,
            "Gigabyte RTX2060 SUPER Gaming OC": false,
            "Gigabyte RTX2060 SUPER Gaming OC 3X 8G V2": false,
            "Gigabyte RTX2060 SUPER Gaming OC 3X White 8G": false,
            "Gigabyte RTX2070 Gaming OC 8G": false,
            "Gigabyte RTX2070 Gaming OC 8GC": false,
            "Gigabyte RTX2070 Windforce 8G": false,
            "Gigabyte RTX2070S Gaming OC": false,
            "Gigabyte RTX2070S Gaming OC 3X": false,
            "Gigabyte RTX2070S Gaming OC 3X White": false,
            "Gigabyte RTX2080 Gaming OC 8G": false,
            "Gigabyte RTX2080 Ti GAMING OC 11G": false,
            "Gigabyte RTX2080S Gaming OC 8G": false,
            "Gigabyte RTX3050 Gaming OC 8G": false,
            "Gigabyte RTX3060 EAGLE 12G LHR V2": false,
            "Gigabyte RTX3060 EAGLE OC 12G": false,
            "Gigabyte RTX3060 EAGLE OC 12G V2": false,
            "Gigabyte RTX3060 Gaming OC 12G": false,
            "Gigabyte RTX3060 Gaming OC 12G (rev. 2.0)": false,
            "Gigabyte RTX3060 Ti EAGLE OC 8G": false,
            "Gigabyte RTX3060 Ti EAGLE OC 8G V2.0 LHR": false,
            "Gigabyte RTX3060 Ti GAMING OC 8G": false,
            "Gigabyte RTX3060 Ti GAMING OC LHR 8G": false,
            "Gigabyte RTX3060 Ti GAMING OC PRO 8G": false,
            "Gigabyte RTX3060 Ti Gaming OC PRO 8G LHR": false,
            "Gigabyte RTX3060 Ti Vision OC 8G": false,
            "Gigabyte RTX3060 Vision OC 12G": false,
            "Gigabyte RTX3060 Vision OC 12G LHR": false,
            "Gigabyte RTX3060 Vision OC 12G v3.0": false,
            "Gigabyte RTX3070 Eagle OC 8G": false,
            "Gigabyte RTX3070 Eagle OC 8G V2.0 LHR": false,
            "Gigabyte RTX3070 Gaming OC 8G": false,
            "Gigabyte RTX3070 Gaming OC 8G v3.0 LHR": false,
            "Gigabyte RTX3070 MASTER 8G": false,
            "Gigabyte RTX3070 MASTER 8G LHR": false,
            "Gigabyte RTX3070 Ti EAGLE 8G": false,
            "Gigabyte RTX3070 Ti Gaming OC 8G": false,
            "Gigabyte RTX3070 Ti Vision OC 8G": false,
            "Gigabyte RTX3070 Vision 8G": false,
            "Gigabyte RTX3070 Vision 8G V2.0 LHR": false,
            "Gigabyte RTX3080 EAGLE OC 10G": false,
            "Gigabyte RTX3080 Gaming OC 10G": false,
            "Gigabyte RTX3080 Gaming OC 12G": false,
            "Gigabyte RTX3080 Ti EAGLE 12G": false,
            "Gigabyte RTX3080 Ti EAGLE OC 12G": false,
            "Gigabyte RTX3080 Ti Gaming OC 12G": false,
            "Gigabyte RTX3080 Ti Vision OC 12G": false,
            "Gigabyte RTX3080 Vision OC 10G": false,
            "Gigabyte RTX3080 Vision OC 10G (REV 2.0)": false,
            "Gigabyte RTX3090 Gaming OC 24G": false,
            "Gigabyte RTX3090 VISION OC 24G ": false,
            "Gigabyte RTX4070Ti Gaming OC 12G": false,
            "Gigabyte RTX4080 AERO OC 16G": false,
            "Gigabyte RTX4080 Eagle OC 16G": false,
            "Gigabyte RTX4080 Gaming OC 16G": false,
            "Gigabyte RTX4090 GAMING OC 24G": false,
            "Glorious Model D / D-": false,
            "Glorious Model D / D- Wireless": false,
            "Glorious Model O / O-": false,
            "Glorious Model O / O- Wireless": false,
            "HP Omen 30L": false,
            "Holtek Mousemat": false,
            "Holtek USB Gaming Mouse": false,
            "HyperX Alloy Elite 2": false,
            "HyperX Alloy Elite 2 (HP)": false,
            "HyperX Alloy Elite RGB": false,
            "HyperX Alloy FPS RGB": false,
            "HyperX Alloy Origins": false,
            "HyperX Alloy Origins (HP)": false,
            "HyperX Alloy Origins 60": false,
            "HyperX Alloy Origins 60 (HP)": false,
            "HyperX Alloy Origins 65 (HP)": false,
            "HyperX Alloy Origins Core": false,
            "HyperX Alloy Origins Core (HP)": false,
            "HyperX DRAM": false,
            "HyperX DuoCast": false,
            "HyperX Fury Ultra": false,
            "HyperX Pulsefire Core": false,
            "HyperX Pulsefire Dart (Wired)": false,
            "HyperX Pulsefire Dart (Wireless)": false,
            "HyperX Pulsefire FPS Pro": false,
            "HyperX Pulsefire Haste": false,
            "HyperX Pulsefire Mat": false,
            "HyperX Pulsefire Mat RGB Mouse Pad XL": false,
            "HyperX Pulsefire Raid": false,
            "HyperX Pulsefire Surge": false,
            "HyperX Quadcast S": false,
            "Intel Arc A770 Limited Edition": false,
            "Ionico Keyboard": false,
            "Ionico Light Bar": false,
            "JSAUX RGB Docking Station": false,
            "KFA2 RTX 2070 EX": false,
            "KFA2 RTX 2080 EX OC": false,
            "KFA2 RTX 2080 Super EX OC": false,
            "KFA2 RTX 2080 TI EX OC": false,
            "KasaSmart": false,
            "Keychron Gaming Keyboard 1": false,
            "LED Strip": false,
            "LIFX": false,
            "Lego Dimensions Toypad Base": false,
            "Lenovo": false,
            "Lenovo 5 2020": false,
            "Lenovo 5 2021": false,
            "Lenovo 5 2022": false,
            "Lenovo Ideapad 3-15ach6": false,
            "Lenovo Legion 7 gen 5": false,
            "Lenovo Legion 7 gen 6": false,
            "Lenovo Legion 7S gen 5": false,
            "Lenovo Legion 7S gen 6": false,
            "Lenovo Legion Y740": false,
            "Lian Li O11 Dynamic - Razer Edition": false,
            "Lian Li Uni Hub": false,
            "Lian Li Uni Hub - AL": false,
            "Lian Li Uni Hub - SL V2": false,
            "Lian Li Uni Hub - SL V2 v0.5": false,
            "Linux LED": true,
            "Logitech G Powerplay Mousepad": false,
            "Logitech G Pro (HERO) Gaming Mouse": false,
            "Logitech G Pro Gaming Mouse": false,
            "Logitech G Pro RGB Mechanical Gaming Keyboard": false,
            "Logitech G Pro Wireless Gaming Mouse": true,
            "Logitech G Pro Wireless Gaming Mouse (wired)": false,
            "Logitech G203 Lightsync": false,
            "Logitech G203 Prodigy": false,
            "Logitech G213": false,
            "Logitech G303 Daedalus Apex": false,
            "Logitech G403 Hero": false,
            "Logitech G403 Prodigy Gaming Mouse": false,
            "Logitech G403 Wireless Gaming Mouse": true,
            "Logitech G403 Wireless Gaming Mouse (wired)": false,
            "Logitech G502 Hero Gaming Mouse": false,
            "Logitech G502 Proteus Spectrum Gaming Mouse": false,
            "Logitech G502 Wireless Gaming Mouse": true,
            "Logitech G502 Wireless Gaming Mouse (wired)": false,
            "Logitech G512": false,
            "Logitech G512 RGB": false,
            "Logitech G560 Lightsync Speaker": false,
            "Logitech G610 Orion": false,
            "Logitech G633 Gaming Headset": false,
            "Logitech G703 Hero Wireless Gaming Mouse": true,
            "Logitech G703 Hero Wireless Gaming Mouse (wired)": false,
            "Logitech G703 Wireless Gaming Mouse": true,
            "Logitech G703 Wireless Gaming Mouse (wired)": false,
            "Logitech G733 Gaming Headset": false,
            "Logitech G810 Orion Spectrum": false,
            "Logitech G813 RGB Mechanical Gaming Keyboard": false,
            "Logitech G815 RGB Mechanical Gaming Keyboard": false,
            "Logitech G900 Wireless Gaming Mouse": true,
            "Logitech G900 Wireless Gaming Mouse (wired)": false,
            "Logitech G903 Hero Wireless Gaming Mouse": true,
            "Logitech G903 Hero Wireless Gaming Mouse (wired)": false,
            "Logitech G903 Wireless Gaming Mouse": true,
            "Logitech G903 Wireless Gaming Mouse (wired)": false,
            "Logitech G910 Orion Spark": false,
            "Logitech G910 Orion Spectrum": false,
            "Logitech G915 Wireless RGB Mechanical Gaming Keyboard": false,
            "Logitech G915 Wireless RGB Mechanical Gaming Keyboard (Wired)": false,
            "Logitech G915TKL Wireless RGB Mechanical Gaming Keyboard": false,
            "Logitech G915TKL Wireless RGB Mechanical Gaming Keyboard (Wired)": false,
            "Logitech G933 Lightsync Headset": false,
            "Logitech G935 Gaming Headset": false,
            "Logitech Lightspeed Receiver": false,
            "Logitech Powerplay Mat": true,
            "Logitech X56 Rhino Hotas Joystick": false,
            "Logitech X56 Rhino Hotas Throttle": false,
            "MSI 3-Zone Laptop": false,
            "MSI GeForce GTX 1070 Gaming X": false,
            "MSI GeForce GTX 1660 Gaming X 6G": false,
            "MSI GeForce GTX 1660 Super Gaming 6G": false,
            "MSI GeForce GTX 1660 Super Gaming X 6G": false,
            "MSI GeForce GTX 1660Ti Gaming 6G": false,
            "MSI GeForce GTX 1660Ti Gaming X 6G": false,
            "MSI GeForce RTX 2060 Gaming Z 6G": false,
            "MSI GeForce RTX 2060 Super ARMOR OC": false,
            "MSI GeForce RTX 2060 Super Gaming X": false,
            "MSI GeForce RTX 2070 ARMOR": false,
            "MSI GeForce RTX 2070 ARMOR OC": false,
            "MSI GeForce RTX 2070 Gaming": false,
            "MSI GeForce RTX 2070 Gaming Z": false,
            "MSI GeForce RTX 2070 SUPER ARMOR OC": false,
            "MSI GeForce RTX 2070 Super Gaming": false,
            "MSI GeForce RTX 2070 Super Gaming Trio": false,
            "MSI GeForce RTX 2070 Super Gaming X": false,
            "MSI GeForce RTX 2070 Super Gaming X Trio": false,
            "MSI GeForce RTX 2070 Super Gaming Z Trio": false,
            "MSI GeForce RTX 2080 Duke 8G OC": false,
            "MSI GeForce RTX 2080 Gaming Trio": false,
            "MSI GeForce RTX 2080 Gaming X Trio": false,
            "MSI GeForce RTX 2080 Sea Hawk EK X": false,
            "MSI GeForce RTX 2080 Super Gaming X Trio": false,
            "MSI GeForce RTX 2080Ti 11G Gaming X Trio": false,
            "MSI GeForce RTX 2080Ti Gaming X Trio": false,
            "MSI GeForce RTX 2080Ti Gaming Z Trio": false,
            "MSI GeForce RTX 2080Ti Sea Hawk EK X": false,
            "MSI GeForce RTX 3050 Gaming X 8G": false,
            "MSI GeForce RTX 3060 12G Gaming X Trio": false,
            "MSI GeForce RTX 3060 12G Gaming X Trio LHR": false,
            "MSI GeForce RTX 3060 12G Gaming Z Trio": false,
            "MSI GeForce RTX 3060 Gaming X 12G": false,
            "MSI GeForce RTX 3060 Gaming X 12G (GA104)": false,
            "MSI GeForce RTX 3060 Gaming X 12G LHR": false,
            "MSI GeForce RTX 3060 Ti 8GB Gaming X LHR": false,
            "MSI GeForce RTX 3060 Ti 8GB Gaming X Trio": false,
            "MSI GeForce RTX 3060 Ti 8GB Gaming X Trio LHR": false,
            "MSI GeForce RTX 3070 8GB Gaming Trio": false,
            "MSI GeForce RTX 3070 8GB Gaming X Trio": false,
            "MSI GeForce RTX 3070 8GB Suprim": false,
            "MSI GeForce RTX 3070 8GB Suprim X": false,
            "MSI GeForce RTX 3070 8GB Suprim X LHR": false,
            "MSI GeForce RTX 3070 Ti 8GB Gaming X Trio": false,
            "MSI GeForce RTX 3070 Ti Suprim X 8G": false,
            "MSI GeForce RTX 3080 10GB Gaming X Trio": false,
            "MSI GeForce RTX 3080 10GB Gaming Z Trio": false,
            "MSI GeForce RTX 3080 10GB Gaming Z Trio LHR": false,
            "MSI GeForce RTX 3080 12GB Gaming Z Trio LHR": false,
            "MSI GeForce RTX 3080 Suprim X 10G": false,
            "MSI GeForce RTX 3080 Suprim X 10G LHR": false,
            "MSI GeForce RTX 3080 Suprim X 12G LHR": false,
            "MSI GeForce RTX 3080 Ti Gaming X Trio 12G": false,
            "MSI GeForce RTX 3080 Ti Suprim X 12G": false,
            "MSI GeForce RTX 3090 24GB Gaming X Trio": false,
            "MSI GeForce RTX 3090 Suprim 24G": false,
            "MSI GeForce RTX 3090 Suprim X 24G": false,
            "MSI GeForce RTX 3090 Ti Gaming X Trio 24G": false,
            "MSI GeForce RTX 3090 Ti Suprim X 24G": false,
            "MSI GeForce RTX 4070 12GB Gaming X Trio": false,
            "MSI GeForce RTX 4070Ti 12GB Gaming X Trio": false,
            "MSI GeForce RTX 4070Ti 12GB Suprim X Trio": false,
            "MSI GeForce RTX 4080 16GB Gaming X Trio": false,
            "MSI GeForce RTX 4080 16GB Suprim X": false,
            "MSI GeForce RTX 4090 24GB Gaming X Trio": false,
            "MSI GeForce RTX 4090 24GB Suprim Liquid X": false,
            "MSI GeForce RTX 4090 24GB Suprim X": false,
            "MSI Mystic Light MS_1562": false,
            "MSI Mystic Light MS_1563": false,
            "MSI Mystic Light MS_1564": false,
            "MSI Mystic Light MS_1720": false,
            "MSI Mystic Light MS_7B12": false,
            "MSI Mystic Light MS_7B16": false,
            "MSI Mystic Light MS_7B17": false,
            "MSI Mystic Light MS_7B18": false,
            "MSI Mystic Light MS_7B50": false,
            "MSI Mystic Light MS_7B85": false,
            "MSI Mystic Light MS_7B93": false,
            "MSI Mystic Light MS_7C34": false,
            "MSI Mystic Light MS_7C35": false,
            "MSI Mystic Light MS_7C36": false,
            "MSI Mystic Light MS_7C37": false,
            "MSI Mystic Light MS_7C56": false,
            "MSI Mystic Light MS_7C59": false,
            "MSI Mystic Light MS_7C60": false,
            "MSI Mystic Light MS_7C67": false,
            "MSI Mystic Light MS_7C71": false,
            "MSI Mystic Light MS_7C73": false,
            "MSI Mystic Light MS_7C75": false,
            "MSI Mystic Light MS_7C76": false,
            "MSI Mystic Light MS_7C77": false,
            "MSI Mystic Light MS_7C79": false,
            "MSI Mystic Light MS_7C80": false,
            "MSI Mystic Light MS_7C81": false,
            "MSI Mystic Light MS_7C82": false,
            "MSI Mystic Light MS_7C83": false,
            "MSI Mystic Light MS_7C84": false,
            "MSI Mystic Light MS_7C86": false,
            "MSI Mystic Light MS_7C87": false,
            "MSI Mystic Light MS_7C90": false,
            "MSI Mystic Light MS_7C91": false,
            "MSI Mystic Light MS_7C92": false,
            "MSI Mystic Light MS_7C94": false,
            "MSI Mystic Light MS_7C95": false,
            "MSI Mystic Light MS_7C98": false,
            "MSI Mystic Light MS_7D03": false,
            "MSI Mystic Light MS_7D06": false,
            "MSI Mystic Light MS_7D07": false,
            "MSI Mystic Light MS_7D08": false,
            "MSI Mystic Light MS_7D09": false,
            "MSI Mystic Light MS_7D13": false,
            "MSI Mystic Light MS_7D15": false,
            "MSI Mystic Light MS_7D17": false,
            "MSI Mystic Light MS_7D18": false,
            "MSI Mystic Light MS_7D19": false,
            "MSI Mystic Light MS_7D20": false,
            "MSI Mystic Light MS_7D25": false,
            "MSI Mystic Light MS_7D27": false,
            "MSI Mystic Light MS_7D28": false,
            "MSI Mystic Light MS_7D29": false,
            "MSI Mystic Light MS_7D30": false,
            "MSI Mystic Light MS_7D31": false,
            "MSI Mystic Light MS_7D32": false,
            "MSI Mystic Light MS_7D36": false,
            "MSI Mystic Light MS_7D38": false,
            "MSI Mystic Light MS_7D41": false,
            "MSI Mystic Light MS_7D42": false,
            "MSI Mystic Light MS_7D43": false,
            "MSI Mystic Light MS_7D46": false,
            "MSI Mystic Light MS_7D50": false,
            "MSI Mystic Light MS_7D51": false,
            "MSI Mystic Light MS_7D52": false,
            "MSI Mystic Light MS_7D53": false,
            "MSI Mystic Light MS_7D54": false,
            "MSI Mystic Light MS_7D59": false,
            "MSI Mystic Light MS_7D67": false,
            "MSI Mystic Light MS_7D69": false,
            "MSI Mystic Light MS_7D70": false,
            "MSI Mystic Light MS_7D73": false,
            "MSI Mystic Light MS_7D75": false,
            "MSI Mystic Light MS_7D76": false,
            "MSI Mystic Light MS_7D77": false,
            "MSI Mystic Light MS_7D78": false,
            "MSI Mystic Light MS_7D86": false,
            "MSI Mystic Light MS_7D89": false,
            "MSI Mystic Light MS_7D91": false,
            "MSI Mystic Light MS_7E01": false,
            "MSI Mystic Light MS_7E06": false,
            "MSI Mystic Light MS_7E07": false,
            "MSI Mystic Light MS_B926": false,
            "MSI Optix controller": false,
            "MSI Radeon RX 6600 XT Gaming X": false,
            "MSI Radeon RX 6700 XT Gaming X": false,
            "MSI Radeon RX 6750 XT Gaming X Trio 12G": false,
            "MSI Radeon RX 6800 Gaming X Trio": false,
            "MSI Radeon RX 6800 Gaming Z Trio v1": false,
            "MSI Radeon RX 6800 XT Gaming X Trio": false,
            "MSI Radeon RX 6800 XT Gaming Z Trio": false,
            "MSI Radeon RX 6900 XT Gaming X Trio": false,
            "MSI Radeon RX 6900 XT Gaming Z Trio": false,
            "MSI Radeon RX 6950 XT Gaming X Trio": false,
            "MSI Vigor GK30 controller": false,
            "MSI-RGB": false,
            "Mountain Everest": false,
            "N5312A USB Optical Mouse": false,
            "NVIDIA RTX2060S": false,
            "NVIDIA RTX2080S": false,
            "NZXT Hue 2": false,
            "NZXT Hue 2 Ambient": false,
            "NZXT Hue 2 Motherboard": false,
            "NZXT Hue+": false,
            "NZXT Kraken M2": false,
            "NZXT Kraken X2": false,
            "NZXT Kraken X3 Series": false,
            "NZXT Kraken X3 Series RGB": false,
            "NZXT RGB & Fan Controller": false,
            "NZXT RGB Controller": false,
            "NZXT Smart Device V1": false,
            "NZXT Smart Device V2": false,
            "Nanoleaf": false,
            "Nollie 32CH": false,
            "Np93 ALPHA - Gaming Mouse": false,
            "Nvidia ESA - Dell XPS 730x": false,
            "OKS Optical Axis RGB": false,
            "OpenRazer": false,
            "PNY XLR8 OC EDITION RTX 2060": false,
            "PNY XLR8 Revel EPIC-X RTX 3060": false,
            "PNY XLR8 Revel EPIC-X RTX 3070": false,
            "PNY XLR8 Revel EPIC-X RTX 3070 LHR": false,
            "PNY XLR8 Revel EPIC-X RTX 3080": false,
            "PNY XLR8 Revel EPIC-X RTX 3090": false,
            "Palit 1080": false,
            "Palit 3060": false,
            "Palit 3060 LHR": false,
            "Palit 3060TI LHR": false,
            "Palit 3060Ti": false,
            "Palit 3070": false,
            "Palit 3070 LHR": false,
            "Palit 3070Ti": false,
            "Palit 3070Ti GamingPro": false,
            "Palit 3080": false,
            "Palit 3080 Gamerock": false,
            "Palit 3080 Gamerock LHR": false,
            "Palit 3080 GamingPro 12G": false,
            "Palit 3080 LHR": false,
            "Palit 3080Ti": false,
            "Palit 3080Ti Gamerock": false,
            "Palit 3090": false,
            "Palit 3090 Gamerock": false,
            "Palit 4070Ti Gamerock": false,
            "Palit 4090 Gamerock": false,
            "Palit GeForce RTX 3060 Ti Dual": false,
            "Patriot Viper": false,
            "Patriot Viper Steel": false,
            "Philips Hue": false,
            "Philips Wiz": false,
            "Razer Abyssus Elite D.Va Edition": false,
            "Razer Abyssus Essential": false,
            "Razer Base Station Chroma": false,
            "Razer Base Station V2 Chroma": false,
            "Razer Basilisk": false,
            "Razer Basilisk Essential": false,
            "Razer Basilisk Ultimate (Wired)": false,
            "Razer Basilisk Ultimate (Wireless)": false,
            "Razer Basilisk V2": false,
            "Razer Basilisk V3": false,
            "Razer Basilisk V3 Pro (Wired)": false,
            "Razer Basilisk V3 Pro (Wireless)": false,
            "Razer Blackwidow 2019": false,
            "Razer Blackwidow Chroma": false,
            "Razer Blackwidow Chroma Tournament Edition": false,
            "Razer Blackwidow Chroma V2": false,
            "Razer Blackwidow Elite": false,
            "Razer Blackwidow Overwatch": false,
            "Razer Blackwidow V3": false,
            "Razer Blackwidow V3 Mini (Wired)": false,
            "Razer Blackwidow V3 Mini (Wireless)": false,
            "Razer Blackwidow V3 Pro (Wired)": false,
            "Razer Blackwidow V3 Pro (Wireless)": false,
            "Razer Blackwidow V3 TKL": false,
            "Razer Blackwidow X Chroma": false,
            "Razer Blackwidow X Chroma Tournament Edition": false,
            "Razer Blade (2016)": false,
            "Razer Blade (Late 2016)": false,
            "Razer Blade 14 (2021)": false,
            "Razer Blade 14 (2022)": false,
            "Razer Blade 15 (2018 Advanced)": false,
            "Razer Blade 15 (2018 Base)": false,
            "Razer Blade 15 (2018 Mercury)": false,
            "Razer Blade 15 (2019 Advanced)": false,
            "Razer Blade 15 (2019 Base)": false,
            "Razer Blade 15 (2019 Mercury)": false,
            "Razer Blade 15 (2019 Studio)": false,
            "Razer Blade 15 (2020 Advanced)": false,
            "Razer Blade 15 (2020 Base)": false,
            "Razer Blade 15 (2021 Advanced)": false,
            "Razer Blade 15 (2021 Base)": false,
            "Razer Blade 15 (2022)": false,
            "Razer Blade 15 (Late 2020)": false,
            "Razer Blade 15 (Late 2021 Advanced)": false,
            "Razer Blade Pro (2016)": false,
            "Razer Blade Pro (2017 FullHD)": false,
            "Razer Blade Pro (2017)": false,
            "Razer Blade Pro (2019)": false,
            "Razer Blade Pro (Late 2019)": false,
            "Razer Blade Pro 17 (2020)": false,
            "Razer Blade Pro 17 (2021)": false,
            "Razer Blade Stealth (2016)": false,
            "Razer Blade Stealth (2017)": false,
            "Razer Blade Stealth (2019)": false,
            "Razer Blade Stealth (2020)": false,
            "Razer Blade Stealth (Late 2016)": false,
            "Razer Blade Stealth (Late 2017)": false,
            "Razer Blade Stealth (Late 2019)": false,
            "Razer Blade Stealth (Late 2020)": false,
            "Razer Book 13 (2020)": false,
            "Razer Charging Pad Chroma": false,
            "Razer Chroma Addressable RGB Controller": false,
            "Razer Chroma HDK": false,
            "Razer Chroma Mug Holder": false,
            "Razer Chroma PC Case Lighting Kit": false,
            "Razer Core": false,
            "Razer Core X": false,
            "Razer Cynosa Chroma": false,
            "Razer Cynosa Chroma V2": false,
            "Razer Cynosa Lite": false,
            "Razer Deathadder Chroma": false,
            "Razer Deathadder Elite": false,
            "Razer Deathadder Essential": false,
            "Razer Deathadder Essential V2": false,
            "Razer Deathadder Essential White Edition": false,
            "Razer Deathadder V2": false,
            "Razer Deathadder V2 Mini": false,
            "Razer Deathadder V2 Pro (Wired)": false,
            "Razer Deathadder V2 Pro (Wireless)": false,
            "Razer Deathstalker Chroma": false,
            "Razer Deathstalker V2": false,
            "Razer Deathstalker V2 Pro (Wired)": false,
            "Razer Deathstalker V2 Pro (Wireless)": false,
            "Razer Diamondback": false,
            "Razer Firefly": false,
            "Razer Firefly Hyperflux": false,
            "Razer Firefly V2": false,
            "Razer Goliathus": false,
            "Razer Goliathus Extended": false,
            "Razer Huntsman": false,
            "Razer Huntsman Elite": false,
            "Razer Huntsman Mini": false,
            "Razer Huntsman Tournament Edition": false,
            "Razer Huntsman V2": false,
            "Razer Huntsman V2 Analog": false,
            "Razer Huntsman V2 TKL": true,
            "Razer Kraken 7.1": false,
            "Razer Kraken 7.1 Chroma": false,
            "Razer Kraken 7.1 V2": false,
            "Razer Kraken Kitty Black Edition": false,
            "Razer Kraken Kitty Edition": false,
            "Razer Kraken Ultimate": false,
            "Razer Lancehead 2017 (Wired)": false,
            "Razer Lancehead 2017 (Wireless)": false,
            "Razer Lancehead 2019 (Wired)": false,
            "Razer Lancehead 2019 (Wireless)": false,
            "Razer Lancehead Tournament Edition": false,
            "Razer Laptop Stand Chroma": false,
            "Razer Laptop Stand Chroma V2": false,
            "Razer Leviathan V2 X": false,
            "Razer Mamba 2012 (Wired)": false,
            "Razer Mamba 2012 (Wireless)": false,
            "Razer Mamba 2015 (Wired)": false,
            "Razer Mamba 2015 (Wireless)": false,
            "Razer Mamba 2018 (Wired)": false,
            "Razer Mamba 2018 (Wireless)": false,
            "Razer Mamba Elite": false,
            "Razer Mamba Tournament Edition": false,
            "Razer Mouse Bungee V3 Chroma": false,
            "Razer Mouse Dock Chroma": false,
            "Razer Mouse Dock Pro": false,
            "Razer Naga Chroma": false,
            "Razer Naga Classic": false,
            "Razer Naga Epic Chroma": false,
            "Razer Naga Hex V2": false,
            "Razer Naga Left Handed": false,
            "Razer Naga Pro (Wired)": false,
            "Razer Naga Pro (Wireless)": false,
            "Razer Naga Trinity": false,
            "Razer Nommo Chroma": false,
            "Razer Nommo Pro": false,
            "Razer Orbweaver Chroma": false,
            "Razer Ornata Chroma": false,
            "Razer Ornata Chroma V2": false,
            "Razer Ornata V3": false,
            "Razer Ornata V3 Rev2": false,
            "Razer Ornata V3 X": false,
            "Razer Seiren Emote": false,
            "Razer Strider Chroma": false,
            "Razer Tartarus Chroma": false,
            "Razer Tartarus Pro": false,
            "Razer Tartarus V2": false,
            "Razer Thunderbolt 4 Dock Chroma": false,
            "Razer Tiamat 7.1 V2": false,
            "Razer Viper": false,
            "Razer Viper 8kHz": false,
            "Razer Viper Mini": false,
            "Razer Viper Ultimate (Wired)": false,
            "Razer Viper Ultimate (Wireless)": false,
            "Red Square Keyrox TKL": false,
            "Red Square Keyrox TKL Classic": false,
            "Redragon M602 Griffin": false,
            "Redragon M711 Cobra": false,
            "Redragon M715 Dagger": false,
            "Redragon M716 Inquisitor": false,
            "Redragon M808 Storm": false,
            "Redragon M908 Impact": false,
            "Roccat Burst Core": false,
            "Roccat Burst Pro": false,
            "Roccat Elo 7.1": false,
            "Roccat Horde Aimo": false,
            "Roccat Kone Aimo": false,
            "Roccat Kone Aimo 16K": false,
            "Roccat Kova": false,
            "Roccat Vulcan 120-Series Aimo": false,
            "SRGBMods LED Controller v1": false,
            "SRGBmods Pico LED Controller": false,
            "Sapphire RX 470/480 Nitro+": false,
            "Sapphire RX 5500 XT Nitro+": false,
            "Sapphire RX 570/580/590 Nitro+": false,
            "Sapphire RX 5700 (XT) Nitro+": false,
            "Sapphire RX 5700 XT Nitro+": false,
            "Sapphire RX 580 Nitro+ (2048SP)": false,
            "Sapphire RX 6600 XT Nitro+": false,
            "Sapphire RX 6700 XT Nitro+": false,
            "Sapphire RX 6750 XT Nitro+": false,
            "Sapphire RX 6800 Nitro+": false,
            "Sapphire RX 6800 XT Nitro+ SE": false,
            "Sapphire RX 6800 XT/6900 XT Nitro+": false,
            "Sapphire RX 6900 XT Nitro+ SE": false,
            "Sapphire RX 6900 XT Toxic": false,
            "Sapphire RX 6900 XT Toxic Limited Edition": false,
            "Sapphire RX 6950 XT Nitro+": false,
            "Sapphire RX 7900 XTX Nitro+": false,
            "Sapphire RX Vega 56/64 Nitro+": false,
            "Sony DualSense": false,
            "Sony DualShock 4": false,
            "SteelSeries Aerox 3 Wired": false,
            "SteelSeries Aerox 9 Wired": false,
            "SteelSeries Apex (OG)/Apex Fnatic": false,
            "SteelSeries Apex 3": false,
            "SteelSeries Apex 3 TKL": false,
            "SteelSeries Apex 350": false,
            "SteelSeries Apex 5": false,
            "SteelSeries Apex 7": false,
            "SteelSeries Apex 7 TKL": false,
            "SteelSeries Apex M750": false,
            "SteelSeries Apex Pro": false,
            "SteelSeries Apex Pro TKL": false,
            "SteelSeries Arctis 5": false,
            "SteelSeries QCK Prism Cloth 3XL": false,
            "SteelSeries QCK Prism Cloth 4XL": false,
            "SteelSeries QCK Prism Cloth Medium": false,
            "SteelSeries QCK Prism Cloth XL": false,
            "SteelSeries QCK Prism Cloth XL CS:GO Neon Rider Ed.": false,
            "SteelSeries QCK Prism Cloth XL Destiny Ed.": false,
            "SteelSeries Rival 100": false,
            "SteelSeries Rival 100 DotA 2 Edition": false,
            "SteelSeries Rival 105": false,
            "SteelSeries Rival 106": false,
            "SteelSeries Rival 110": false,
            "SteelSeries Rival 3": false,
            "SteelSeries Rival 3 (Old Firmware)": false,
            "SteelSeries Rival 300": false,
            "SteelSeries Rival 300 Black Ops Edition": false,
            "SteelSeries Rival 300 CS:GO Fade Edition": false,
            "SteelSeries Rival 300 CS:GO Fade Edition (stm32)": false,
            "SteelSeries Rival 300 CS:GO Hyperbeast Edition": false,
            "SteelSeries Rival 300 Dota 2 Edition": false,
            "SteelSeries Rival 300 HP Omen Edition": false,
            "SteelSeries Rival 310": false,
            "SteelSeries Rival 310 CS:GO Howl Edition": false,
            "SteelSeries Rival 310 PUBG Edition": false,
            "SteelSeries Rival 600": false,
            "SteelSeries Rival 600 Dota 2 Edition": false,
            "SteelSeries Rival 650": false,
            "SteelSeries Rival 650 Wireless": false,
            "SteelSeries Rival 700": false,
            "SteelSeries Rival 710": false,
            "SteelSeries Sensei 310": false,
            "SteelSeries Sensei TEN": false,
            "SteelSeries Sensei TEN CS:GO Neon Rider Edition": false,
            "SteelSeries Siberia 350": false,
            "Strimer L Connect": false,
            "Tecknet M008": false,
            "Thermaltake Poseidon Z RGB": false,
            "Thermaltake Riing (PID 0x1FA5)": false,
            "Thermaltake Riing (PID 0x1FA6)": false,
            "Thermaltake Riing (PID 0x1FA7)": false,
            "Thermaltake Riing (PID 0x1FA8)": false,
            "Thermaltake Riing (PID 0x1FA9)": false,
            "Thermaltake Riing (PID 0x1FAA)": false,
            "Thermaltake Riing (PID 0x1FAB)": false,
            "Thermaltake Riing (PID 0x1FAC)": false,
            "Thermaltake Riing (PID 0x1FAD)": false,
            "Thermaltake Riing (PID 0x1FAE)": false,
            "Thermaltake Riing (PID 0x1FAF)": false,
            "Thermaltake Riing (PID 0x1FB0)": false,
            "Thermaltake Riing (PID 0x1FB1)": false,
            "Thermaltake Riing (PID 0x1FB2)": false,
            "Thermaltake Riing (PID 0x1FB3)": false,
            "Thermaltake Riing (PID 0x1FB4)": false,
            "Thermaltake Riing (PID 0x1FB5)": false,
            "Thermaltake Riing Quad (PID 0x2260)": false,
            "Thermaltake Riing Quad (PID 0x2261)": false,
            "Thermaltake Riing Quad (PID 0x2262)": false,
            "Thermaltake Riing Quad (PID 0x2263)": false,
            "Thermaltake Riing Quad (PID 0x2264)": false,
            "Thermaltake Riing Quad (PID 0x2265)": false,
            "Thermaltake Riing Quad (PID 0x2266)": false,
            "Thermaltake Riing Quad (PID 0x2267)": false,
            "Thermaltake Riing Quad (PID 0x2268)": false,
            "Thermaltake Riing Quad (PID 0x2269)": false,
            "Thermaltake Riing Quad (PID 0x226A)": false,
            "Thermaltake Riing Quad (PID 0x226B)": false,
            "Thermaltake Riing Quad (PID 0x226C)": false,
            "Thermaltake Riing Quad (PID 0x226D)": false,
            "Thermaltake Riing Quad (PID 0x226E)": false,
            "Thermaltake Riing Quad (PID 0x226F)": false,
            "Thermaltake Riing Quad (PID 0x2270)": false,
            "ThingM blink(1) mk2": false,
            "Trust GXT 114": false,
            "Trust GXT 180": false,
            "ViewSonic Monitor XG270QG": false,
            "Wooting One (Classic)": false,
            "Wooting One (Legacy)": false,
            "Wooting One (None)": false,
            "Wooting One (Xbox)": false,
            "Wooting Two (Classic)": false,
            "Wooting Two (Legacy)": false,
            "Wooting Two (None)": false,
            "Wooting Two (Xbox)": false,
            "Wooting Two 60HE (ARM) (Classic)": false,
            "Wooting Two 60HE (ARM) (None)": false,
            "Wooting Two 60HE (ARM) (Xbox)": false,
            "Wooting Two 60HE (Classic)": false,
            "Wooting Two 60HE (None)": false,
            "Wooting Two 60HE (Xbox)": false,
            "Wooting Two HE (ARM) (Classic)": false,
            "Wooting Two HE (ARM) (None)": false,
            "Wooting Two HE (ARM) (Xbox)": false,
            "Wooting Two HE (Classic)": false,
            "Wooting Two HE (None)": false,
            "Wooting Two HE (Xbox)": false,
            "Wooting Two LE (Classic)": false,
            "Wooting Two LE (None)": false,
            "Wooting Two LE (Xbox)": false,
            "XPG Spectrix S40G": true,
            "Yeelight": false,
            "ZET Blade Optical": false,
            "ZET Fury Pro": false,
            "ZET GAMING Edge Air Elit": false,
            "ZET GAMING Edge Air Elit (Wireless)": false,
            "ZET GAMING Edge Air Pro": false,
            "ZET GAMING Edge Air Pro (Wireless)": false,
            "ZOTAC GAMING GeForce RTX 2070 SUPER Twin Fan": false,
            "ZOTAC GAMING GeForce RTX 3070 Ti Trinity OC": false,
            "ZOTAC GAMING GeForce RTX 3080 Ti AMP Holo": false,
            "ZOTAC GAMING GeForce RTX 3090 AMP Extreme Holo": false,
            "ZOTAC GAMING GeForce RTX 4090 AMP Extreme AIRO": false,
            "ZOTAC GAMING GeForce RTX 4090 Trinity OC": false,
            "Zalman Z Sync": false,
            "iGame GeForce RTX 2070 SUPER Advanced OC-V": false,
            "iGame GeForce RTX 3060 Advanced OC 12G L-V": false,
            "iGame GeForce RTX 3060 Ti Advanced OC-V": false,
            "iGame GeForce RTX 3060 Ti Ultra W OC LHR-V": false,
            "iGame GeForce RTX 3060 Ultra W OC 12G L-V": false,
            "iGame GeForce RTX 3070 Advanced OC-V": false,
            "iGame GeForce RTX 3070 Ti Advanced OC-V": false,
            "iGame GeForce RTX 3070 Ti Ultra W OC LHR": false,
            "iGame GeForce RTX 3070 Ultra W OC LHR": false,
            "iGame GeForce RTX 3080 Ti Advanced OC-V": false,
            "iGame GeForce RTX 4070 Ti Advanced OC-V": false,
            "iGame GeForce RTX 4080 Ultra W OC-V": false
        }
    },
    "Gigabyte RGB Fusion 2 SMBus": {
        "SupportedDevices": [
            "B450 AORUS ELITE",
            "B450 AORUS ELITE V2",
            "B450 AORUS M",
            "B450 AORUS PRO WIFI-CF",
            "B450 AORUS PRO-CF",
            "B450 AORUS PRO-CF4",
            "B450 I AORUS PRO WIFI-CF",
            "B450M DS3H-CF",
            "X299 DESIGNARE EX-CF",
            "X399 AORUS XTREME-CF",
            "X399 DESIGNARE EX-CF",
            "X470 AORUS GAMING 5 WIFI",
            "X470 AORUS GAMING 5 WIFI-CF",
            "X470 AORUS GAMING 7 WIFI-CF",
            "X470 AORUS GAMING 7 WIFI-50-CF",
            "X470 AORUS ULTRA GAMING",
            "X470 AORUS ULTRA GAMING-CF",
            "B360M AORUS Gaming 3-CF",
            "Z370 AORUS Gaming 5-CF",
            "Z370 AORUS Ultra Gaming-CF"
        ]
    },
    "LogManager": {
        "dialog_no_show_hashes": [
            6856110824172292845
        ]
    },
    "Plugins": {
        "plugins": [
            {
                "description": "Provides a variety of custom effects",
                "enabled": true,
                "name": "OpenRGB Effects Plugin"
            },
            {
                "description": "Sync colors with hardware measures",
                "enabled": true,
                "name": "Hardware Sync"
            }
        ]
    },
    "Theme": {
        "theme": "auto"
    },
    "UserInterface": {
        "RunZoneChecks": true,
        "exit_profile": {
            "profile_name": "Light green",
            "set_on_exit": false
        },
        "geometry": {
            "height": 0,
            "load_geometry": false,
            "save_on_exit": false,
            "width": 0,
            "x": 0,
            "y": 0
        },
        "greyscale_tray_icon": true,
        "language": "Franais",
        "minimize_on_close": true
    }
}